CHANGELOG.rst
LICENSE
MANIFEST.in
README.rst
setup.py
docs/Makefile
docs/api.rst
docs/conf.py
docs/custom-sdof-system.rst
docs/examples.rst
docs/forcing.rst
docs/index.rst
docs/make.bat
docs/outline.rst
resonance/__init__.py
resonance/functions.py
resonance/linear_systems.py
resonance/nonlinear_systems.py
resonance/system.py
resonance/version.py
resonance.egg-info/PKG-INFO
resonance.egg-info/SOURCES.txt
resonance.egg-info/dependency_links.txt
resonance.egg-info/requires.txt
resonance.egg-info/top_level.txt
resonance/tests/__init__.py
resonance/tests/test_linear_systems.py
resonance/tests/test_nonlinear_systems.py
resonance/tests/test_systems.py