Metadata-Version: 2.1
Name: resonance
Version: 0.22.0
Summary: Learning mechanical vibrations through computation.
Home-page: https://github.com/moorepants/resonance/
Author: Jason K. Moore
Author-email: moorepants@gmail.com
License: MIT
Keywords: engineering vibrations mechanical simulation
Platform: UNKNOWN
Classifier: Development Status :: 4 - Beta
Classifier: Intended Audience :: Science/Research
Classifier: Operating System :: OS Independent
Classifier: Programming Language :: Python :: 3.6
Classifier: Programming Language :: Python :: 3.7
Classifier: Programming Language :: Python :: 3.8
Classifier: Topic :: Scientific/Engineering :: Physics
Provides-Extra: notebooks
